{
  "project_info": {
    "project_number": "359331886853",
    "firebase_url": "https://fileupload-44e02.firebaseio.com",
    "project_id": "fileupload-44e02",
    "storage_bucket": "fileupload-44e02.appspot.com"
  },
  "client": [
    {
      "client_info": {
        "mobilesdk_app_id": "1:359331886853:android:c6cc038df17913e583296c",
        "android_client_info": {
          "package_name": "com.example.fileupload"
        }
      },
      "oauth_client": [
        {
          "client_id": "359331886853-38kpo1issv8dsmsfkl17a8mav15468hg.apps.googleusercontent.com",
          "client_type": 1,
          "android_info": {
            "package_name": "com.example.fileupload",
            "certificate_hash": "c86ee36a403378a2d67dbddc010f7f1c7f263820"
          }
        },
        {
          "client_id": "359331886853-sfoi2cl3s0lvp7oodrosmprjbudls0uk.apps.googleusercontent.com",
          "client_type": 3
        }
      ],
      "api_key": [
        {
          "current_key": "AIzaSyDel-NWFo6T-0Dk6UT9t-yAjO6wngrOi9Q"
        }
      ],
      "services": {
        "appinvite_service": {
          "other_platform_oauth_client": [
            {
              "client_id": "359331886853-sfoi2cl3s0lvp7oodrosmprjbudls0uk.apps.googleusercontent.com",
              "client_type": 3
            }
          ]
        }
      }
    }
  ],
  "configuration_version": "1"
}